__init__.py
brine_density.py
thermalift.py
thermalift-1.0.2.dist-info/licenses/LICENSE
thermalift-1.0.2.dist-info/METADATA
thermalift-1.0.2.dist-info/WHEEL
thermalift-1.0.2.dist-info/top_level.txt
thermalift-1.0.2.dist-info/RECORD
