Metadata-Version: 2.4
Name: Thermalift
Version: 1.0.2
Summary: Calculator of the thermal lift effect in geothermal wells
Author-email: Maciej Miecznik <miecznik@min-pan.krakow.pl>
License-Expression: BSD-3-Clause
Project-URL: Homepage, https://github.com/maciejmiecznik/Thermalift/tree/main
Project-URL: Issues, https://github.com/maciejmiecznik/Thermalift/issues
Keywords: geothermal,well test,reservoir engineering
Classifier: Programming Language :: Python :: 3
Classifier: Operating System :: OS Independent
Classifier: Topic :: Scientific/Engineering
Requires-Python: >=3.11
License-File: LICENSE
Dynamic: license-file
